README.md
setup.py
src/sentry_feishu/__init__.py
src/sentry_feishu/forms.py
src/sentry_feishu/plugin.py
src/sentry_feishu.egg-info/PKG-INFO
src/sentry_feishu.egg-info/SOURCES.txt
src/sentry_feishu.egg-info/dependency_links.txt
src/sentry_feishu.egg-info/entry_points.txt
src/sentry_feishu.egg-info/not-zip-safe
src/sentry_feishu.egg-info/requires.txt
src/sentry_feishu.egg-info/top_level.txt