Metadata-Version: 2.1
Name: sentry-feishu
Version: 0.0.1
Summary: A Sentry extension which send errors stats to DingDing
Home-page: https://github.com/jnchenfeng/sentry_feishu
Author: feng.chen
Author-email: jnchenfeng123@163.com
License: MIT
Keywords: sentry feishu
Platform: UNKNOWN
Classifier: Programming Language :: Python :: 2.7
Classifier: License :: OSI Approved :: MIT License
